unitauto/__init__.py
unitauto/methodutil.py
unitauto/server.py
unitauto/test/__init__.py
unitauto/test/testutil.py
unitauto-1.1.0.dist-info/LICENSE
unitauto-1.1.0.dist-info/METADATA
unitauto-1.1.0.dist-info/WHEEL
unitauto-1.1.0.dist-info/top_level.txt
unitauto-1.1.0.dist-info/RECORD
