Metadata-Version: 2.1
Name: unitauto
Version: 1.1.0
Summary: An unit testing platform powered by machine learning. Coding-free, comprehensive and automatic testing for methods/functions
Home-page: https://github.com/TommyLemon/unitauto-py
Author: TommyLemon
Author-email: tommylemon@qq.com
Classifier: Programming Language :: Python :: 3
Classifier: License :: OSI Approved :: MIT License
Classifier: Operating System :: OS Independent
Requires-Python: >=3.7
License-File: LICENSE
